pystartrails/__init__.py
pystartrails/generator/__init__.py
pystartrails/generator/trails_and_timelapse_generator.py
pystartrails/tests/__init__.py
pystartrails/tests/tester.py
pystartrails-0.1.0.dist-info/licenses/LICENSE
pystartrails-0.1.0.dist-info/METADATA
pystartrails-0.1.0.dist-info/WHEEL
pystartrails-0.1.0.dist-info/top_level.txt
pystartrails-0.1.0.dist-info/RECORD
