Metadata-Version: 2.4
Name: pystartrails
Version: 0.1.0
Summary: Generate stunning star trail images and time-lapse videos from night sky image sequences
Home-page: https://github.com/yassirlairgi/PyStarTrails
Author: Yassir LAIRGI
Author-email: yassirlairgi@gmail.com
License: MIT
Project-URL: Documentation, https://github.com/yassirlairgi/PyStarTrails
Project-URL: Source, https://github.com/yassirlairgi/PyStarTrails
Project-URL: Tracker, https://github.com/yassirlairgi/PyStarTrails/issues
Keywords: python,star trails,astrophotography,photography,blending modes,time-lapse,image processing,astronomy
Classifier: Development Status :: 4 - Beta
Classifier: Intended Audience :: Developers
Classifier: Intended Audience :: Science/Research
Classifier: License :: OSI Approved :: MIT License
Classifier: Operating System :: OS Independent
Classifier: Programming Language :: Python :: 3
Classifier: Programming Language :: Python :: 3.7
Classifier: Programming Language :: Python :: 3.8
Classifier: Programming Language :: Python :: 3.9
Classifier: Programming Language :: Python :: 3.10
Classifier: Programming Language :: Python :: 3.11
Classifier: Topic :: Multimedia :: Graphics :: Graphics Conversion
Classifier: Topic :: Scientific/Engineering :: Image Processing
Classifier: Topic :: Scientific/Engineering :: Astronomy
Requires-Python: >=3.7
License-File: LICENSE
Requires-Dist: matplotlib
Requires-Dist: numpy<2
Requires-Dist: opencv-python>=4.6.0
Requires-Dist: setuptools
Requires-Dist: tqdm>=4.64.0
Dynamic: license-file
